{
  "context": {
    "friends_who_like": {
      "data": [],
      "summary": {
        "social_sentence": "14 of your friends like this.",
        "total_count": 14
      }
    }
  },
  "parking": {
    "lot": 0,
    "street": 0,
    "valet": 0
  },
  "restaurant_services": {
    "delivery": 0,
    "catering": 0,
    "groups": 1,
    "kids": 0,
    "outdoor": 0,
    "reserve": 1,
    "takeout": 0,
    "waiter": 0,
    "walkins": 1
  },
  "restaurant_specialties": {
    "breakfast": 0,
    "coffee": 0,
    "dinner": 1,
    "drinks": 0,
    "lunch": 0
  },
  "payment_options": {
    "amex": 1,
    "cash_only": 0,
    "discover": 0,
    "mastercard": 1,
    "visa": 1
  },
  "id": "139296106095829"
}
